annexremote/__init__.py
annexremote/_version.py
annexremote/annexremote.py
annexremote-1.6.6.dist-info/LICENSE
annexremote-1.6.6.dist-info/METADATA
annexremote-1.6.6.dist-info/WHEEL
annexremote-1.6.6.dist-info/top_level.txt
annexremote-1.6.6.dist-info/RECORD
