Metadata-Version: 2.1
Name: annexremote
Version: 1.6.6
Summary: git annex special remotes made easy
Author-email: Silvio Ankermann <silvio@booq.org>
License: GPL-3.0-only
Project-URL: Documentation, https://lykos153.github.io/AnnexRemote
Project-URL: Source, https://github.com/Lykos153/AnnexRemote
Keywords: git-annex,remote
Classifier: Development Status :: 5 - Production/Stable
Classifier: Intended Audience :: Developers
Classifier: Topic :: Software Development :: Libraries :: Python Modules
Classifier: License :: OSI Approved :: GNU General Public License v3 (GPLv3)
Classifier: Programming Language :: Python :: 3.7
Classifier: Programming Language :: Python :: 3.8
Classifier: Programming Language :: Python :: 3.9
Classifier: Programming Language :: Python :: 3.10
Classifier: Programming Language :: Python :: 3.11
License-File: LICENSE
Provides-Extra: tests
Requires-Dist: coverage; extra == "tests"
Requires-Dist: pytest; extra == "tests"
Provides-Extra: doc
Requires-Dist: sphinx; extra == "doc"
